karrio/mappers/sapient/__init__.py
karrio/mappers/sapient/mapper.py
karrio/mappers/sapient/proxy.py
karrio/mappers/sapient/settings.py
karrio/plugins/sapient/__init__.py
karrio/providers/sapient/__init__.py
karrio/providers/sapient/error.py
karrio/providers/sapient/units.py
karrio/providers/sapient/utils.py
karrio/providers/sapient/pickup/__init__.py
karrio/providers/sapient/pickup/cancel.py
karrio/providers/sapient/pickup/create.py
karrio/providers/sapient/pickup/update.py
karrio/providers/sapient/shipment/__init__.py
karrio/providers/sapient/shipment/cancel.py
karrio/providers/sapient/shipment/create.py
karrio/schemas/sapient/__init__.py
karrio/schemas/sapient/error_response.py
karrio/schemas/sapient/pickup_request.py
karrio/schemas/sapient/pickup_response.py
karrio/schemas/sapient/shipment_requests.py
karrio/schemas/sapient/shipment_response.py
karrio_sapient-2026.1.4.dist-info/METADATA
karrio_sapient-2026.1.4.dist-info/WHEEL
karrio_sapient-2026.1.4.dist-info/entry_points.txt
karrio_sapient-2026.1.4.dist-info/top_level.txt
karrio_sapient-2026.1.4.dist-info/RECORD
